{
    "os": "Linux-5.15.0-89-generic-x86_64-with-glibc2.35",
    "python": "3.10.12",
    "heartbeatAt": "2023-12-11T12:24:43.966049",
    "startedAt": "2023-12-11T12:24:42.740523",
    "docker": null,
    "cuda": null,
    "args": [],
    "state": "running",
    "program": "<python with no main file>",
    "codePathLocal": null,
    "git": {
        "remote": "https://github.com/shannentan22/CS198Repository.git",
        "commit": "068d55377a1c937f51d0fa34e90418527a939ab4"
    },
    "email": "shannentan22@gmail.com",
    "root": "/home/nlpbiodiv2023/CS198Repository",
    "host": "io",
    "username": "nlpbiodiv2023",
    "executable": "/bin/python3",
    "cpu_count": 6,
    "cpu_count_logical": 6,
    "cpu_freq": {
        "current": 1900.0,
        "min": 800.0,
        "max": 1900.0
    },
    "cpu_freq_per_core": [
        {
            "current": 1900.0,
            "min": 800.0,
            "max": 1900.0
        },
        {
            "current": 1900.0,
            "min": 800.0,
            "max": 1900.0
        },
        {
            "current": 1899.999,
            "min": 800.0,
            "max": 1900.0
        },
        {
            "current": 1900.0,
            "min": 800.0,
            "max": 1900.0
        },
        {
            "current": 1900.001,
            "min": 800.0,
            "max": 1900.0
        },
        {
            "current": 1900.0,
            "min": 800.0,
            "max": 1900.0
        }
    ],
    "disk": {
        "/": {
            "total": 915.3232879638672,
            "used": 299.443904876709
        }
    },
    "gpu": "NVIDIA GeForce RTX 3060",
    "gpu_count": 2,
    "gpu_devices": [
        {
            "name": "NVIDIA GeForce RTX 3060",
            "memory_total": 12884901888
        },
        {
            "name": "NVIDIA GeForce RTX 3060",
            "memory_total": 12884901888
        }
    ],
    "memory": {
        "total": 30.991832733154297
    }
}
